iamzero/__init__.py
iamzero/client.py
iamzero/config.py
iamzero/event.py
iamzero/identity.py
iamzero/instrumentation/__init__.py
iamzero/instrumentation/botocore.py
iamzero/logging.py
iamzero/publisher.py
iamzero/test_config.py
iamzero/version.py
iamzero-0.1.4.dist-info/WHEEL
iamzero-0.1.4.dist-info/METADATA
iamzero-0.1.4.dist-info/RECORD
