Metadata-Version: 2.1
Name: iamzero
Version: 0.1.4
Summary: iam-zero least-privilege instrumentation client for Python
Home-page: https://iamzero.dev
License: Apache-2.0
Author: Common Fate
Author-email: hello@commonfate.io
Requires-Python: >=3.6.2,<4.0.0
Classifier: Development Status :: 3 - Alpha
Classifier: Intended Audience :: Developers
Classifier: License :: OSI Approved :: Apache Software License
Classifier: Programming Language :: Python :: 3
Classifier: Programming Language :: Python :: 3.7
Classifier: Programming Language :: Python :: 3.8
Classifier: Programming Language :: Python :: 3.9
Classifier: Topic :: Security
Classifier: Topic :: Software Development :: Libraries
Requires-Dist: requests (>=2.25.1,<3.0.0)
Requires-Dist: statsd (>=3.3.0,<4.0.0)
Requires-Dist: wrapt (>=1.12.1,<2.0.0)
Project-URL: Documentation, https://iamzero.dev/docs/getting-started
